{
  "d7b96e10-7cea-4b62-8d1e-0921e94c4b95": {
    "created_at": "2025-12-11",
    "faves_count": 1,
    "taxon_id": 850858
  },
  "856b1934-ea5b-494e-bc11-b47d367b0efc": {
    "created_at": "2025-12-10",
    "faves_count": 1,
    "taxon_id": 12707
  },
  "131be66c-762d-445b-96d9-680ab33bd22d": {
    "created_at": "2025-12-10",
    "faves_count": 1,
    "taxon_id": 1589675
  },
  "8433fa7f-562c-4bc6-855e-f61bae2fd463": {
    "created_at": "2025-12-09",
    "faves_count": 1,
    "taxon_id": 203153
  },
  "129b7f32-fb60-4cad-9318-6e7c97edf44c": {
    "created_at": "2025-12-08",
    "faves_count": 1,
    "taxon_id": 3048
  },
  "4f88e6f5-7b6c-4e09-9088-ab5d4d62e549": {
    "created_at": "2025-12-08",
    "faves_count": 1,
    "taxon_id": 17669
  },
  "54fea29e-b764-41ec-94b2-b364255e326b": {
    "created_at": "2025-12-08",
    "faves_count": 1,
    "taxon_id": 6930
  },
  "f0931d97-903d-4880-8db8-fd7e13d7ea2d": {
    "created_at": "2025-12-07",
    "faves_count": 1,
    "taxon_id": 117016
  },
  "f1b2be6d-74b8-462c-a4da-62dfd5801c9b": {
    "created_at": "2025-12-07",
    "faves_count": 1,
    "taxon_id": 12748
  },
  "84aa2ba0-80bd-4bdf-a0b9-f8ccbaea6e3d": {
    "created_at": "2025-12-07",
    "faves_count": 1,
    "taxon_id": 145360
  },
  "82c26890-a5c0-40f4-93e9-2e6fbd6b4d14": {
    "created_at": "2025-12-07",
    "faves_count": 1,
    "taxon_id": 116804
  },
  "bbff9fd5-5e0e-43e4-9038-d3311c6f8713": {
    "created_at": "2025-12-06",
    "faves_count": 1,
    "taxon_id": 3048
  },
  "93a0877c-71a1-43b6-9fa8-739e7f39a876": {
    "created_at": "2025-12-06",
    "faves_count": 1,
    "taxon_id": 116791
  },
  "306d07ba-6671-46b2-9526-2ae151067c35": {
    "created_at": "2025-12-06",
    "faves_count": 1,
    "taxon_id": 204552
  },
  "08c9537b-b742-496e-8d80-3c10954bdf04": {
    "created_at": "2025-12-06",
    "faves_count": 1,
    "taxon_id": 5325
  },
  "2b370c34-5c18-41ae-b6b8-d195908a6513": {
    "created_at": "2025-12-06",
    "faves_count": 1,
    "taxon_id": 4643
  },
  "f8cbc92f-3eb4-44ed-8fbe-9d7544b8417a": {
    "created_at": "2025-12-05",
    "faves_count": 1,
    "taxon_id": 792977
  },
  "35d8b81b-1a39-4388-8d23-17e1826abaca": {
    "created_at": "2025-12-05",
    "faves_count": 1,
    "taxon_id": 145300
  },
  "61369e45-ab56-4d25-9088-64ecfaa8712d": {
    "created_at": "2025-12-04",
    "faves_count": 1,
    "taxon_id": 558596
  },
  "12346597-0dc5-4ded-a5e7-016476ea34c6": {
    "created_at": "2025-12-02",
    "faves_count": 1,
    "taxon_id": 4450
  },
  "10cfef08-ccae-4945-81f7-05de973e0ccb": {
    "created_at": "2025-12-02",
    "faves_count": 1,
    "taxon_id": 19910
  },
  "e863becb-9018-4e9a-bf83-bd6091d1209c": {
    "created_at": "2025-11-29",
    "faves_count": 1,
    "taxon_id": 144757
  },
  "717c9a0e-c7ba-46c1-9668-5a9dedb8ca5b": {
    "created_at": "2025-11-28",
    "faves_count": 1,
    "taxon_id": 5242
  },
  "29991d84-4afb-4908-baf7-c1061e73e551": {
    "created_at": "2025-11-19",
    "faves_count": 1,
    "taxon_id": 363896
  },
  "192fc250-3e8c-42fa-8fc7-53c72050ca45": {
    "created_at": "2025-11-17",
    "faves_count": 1,
    "taxon_id": 145300
  },
  "4db73bc9-74fd-4f72-9296-9ee04f500f4a": {
    "created_at": "2025-11-17",
    "faves_count": 1,
    "taxon_id": 7647
  },
  "a6b3e372-4fcc-400d-964d-75b5abd0eb70": {
    "created_at": "2025-11-16",
    "faves_count": 1,
    "taxon_id": 558596
  },
  "5b924dba-2be5-46aa-a6a7-11faa2ab9fe8": {
    "created_at": "2025-11-16",
    "faves_count": 1,
    "taxon_id": 4205
  },
  "e6ff8f08-b802-4b5d-9a32-bc562c585802": {
    "created_at": "2025-11-16",
    "faves_count": 1,
    "taxon_id": 6930
  },
  "742b9883-fad5-44fa-9654-970e1116dfed": {
    "created_at": "2025-11-16",
    "faves_count": 1,
    "taxon_id": 4205
  },
  "6317d7f0-fb11-41ce-98f5-bb6a7655e588": {
    "created_at": "2025-11-16",
    "faves_count": 1,
    "taxon_id": 558596
  },
  "65bc18f0-56d7-4c81-87a0-a835c2143842": {
    "created_at": "2025-11-16",
    "faves_count": 1,
    "taxon_id": 203153
  },
  "a208e7ce-86ff-4a64-846d-6b4569ad6e98": {
    "created_at": "2025-11-14",
    "faves_count": 1,
    "taxon_id": 144455
  },
  "12bbafe2-8879-4da7-95aa-59a8a0914a44": {
    "created_at": "2025-11-13",
    "faves_count": 1,
    "taxon_id": 558596
  },
  "782233fe-ef63-45cf-b651-7216752848c9": {
    "created_at": "2025-11-13",
    "faves_count": 1,
    "taxon_id": 558596
  },
  "e428b52e-1561-4ea1-b32e-cc734b97393c": {
    "created_at": "2025-11-13",
    "faves_count": 1,
    "taxon_id": 203153
  },
  "33976612-d7e1-4383-acc1-7d78f86eada4": {
    "created_at": "2025-11-12",
    "faves_count": 1,
    "taxon_id": 339593
  },
  "bf376a6d-493a-45e0-8ef8-5a0cbdcbdc39": {
    "created_at": "2025-11-12",
    "faves_count": 1,
    "taxon_id": 558438
  },
  "41ea2bd7-206b-441c-974d-18362a263f38": {
    "created_at": "2025-11-12",
    "faves_count": 2,
    "taxon_id": 558429
  },
  "4ff6c397-5b3b-4a82-999a-c6282f88ce0f": {
    "created_at": "2025-11-06",
    "faves_count": 1,
    "taxon_id": 236935
  },
  "2c6f514e-dc9d-4503-be2e-a11aac268270": {
    "created_at": "2025-11-04",
    "faves_count": 1,
    "taxon_id": 3931
  },
  "a25cf490-8daf-45f8-96a9-57cefcfa6544": {
    "created_at": "2025-11-02",
    "faves_count": 1,
    "taxon_id": 17943
  },
  "e9190107-fc18-4a1f-8573-0c380a018843": {
    "created_at": "2025-11-02",
    "faves_count": 1,
    "taxon_id": 831
  },
  "c656038e-d98c-46f4-b244-3a4089153568": {
    "created_at": "2025-11-01",
    "faves_count": 1,
    "taxon_id": 13724
  },
  "7a7a329a-4361-4051-be87-7307c1010a14": {
    "created_at": "2025-10-29",
    "faves_count": 1,
    "taxon_id": 558596
  },
  "b2c3f2fe-6b6c-41bc-b7c6-a7f0162ff764": {
    "created_at": "2025-10-27",
    "faves_count": 1,
    "taxon_id": 5200
  },
  "c598524b-efb3-4cb7-8c1a-45bc3f7098ea": {
    "created_at": "2025-10-22",
    "faves_count": 1,
    "taxon_id": 792977
  },
  "e04ca6de-55da-4752-92a7-f8539f3684a3": {
    "created_at": "2025-10-21",
    "faves_count": 1,
    "taxon_id": 4647
  },
  "28a2dde7-7e0f-44c9-9537-a7bb1016c625": {
    "created_at": "2025-10-19",
    "faves_count": 1,
    "taxon_id": 558596
  },
  "c2a7597a-38fa-4cba-9ba8-c17d5582cbb4": {
    "created_at": "2025-10-17",
    "faves_count": 1,
    "taxon_id": 10069
  },
  "fb97e69e-5c9d-4013-bf4d-fb54b467fa71": {
    "created_at": "2025-10-15",
    "faves_count": 1,
    "taxon_id": 558596
  },
  "fea14557-e224-4983-81fa-e3b8c0d27742": {
    "created_at": "2025-10-09",
    "faves_count": 1,
    "taxon_id": 1289697
  },
  "245a1e87-6f1a-4b30-996f-237134cddfac": {
    "created_at": "2025-10-07",
    "faves_count": 1,
    "taxon_id": 9201
  },
  "6f22e371-f308-4fd5-ba7b-aa7012edd01a": {
    "created_at": "2025-10-06",
    "faves_count": 1,
    "taxon_id": 558596
  },
  "4f152d94-d6b3-4302-9aa3-c39510bbc927": {
    "created_at": "2025-10-05",
    "faves_count": 1,
    "taxon_id": 7450
  },
  "fe78e2d8-120a-41d4-887c-829aa0d388d8": {
    "created_at": "2025-10-01",
    "faves_count": 1,
    "taxon_id": 4224
  },
  "00db004b-e05b-4cab-9224-89bbe368e235": {
    "created_at": "2025-09-27",
    "faves_count": 1,
    "taxon_id": 9210
  },
  "d1054c83-5f01-4300-b8a1-35e74954bb68": {
    "created_at": "2025-09-24",
    "faves_count": 1,
    "taxon_id": 339593
  },
  "267a1160-6af5-4e16-bcc2-4a9387897ec2": {
    "created_at": "2025-09-24",
    "faves_count": 1,
    "taxon_id": 19890
  },
  "26737217-dfaf-48bf-8146-f91276b63c9c": {
    "created_at": "2025-09-21",
    "faves_count": 1,
    "taxon_id": 1026
  },
  "35e7dbe1-56a6-43ae-9532-fb93a7c4c5be": {
    "created_at": "2025-09-20",
    "faves_count": 1,
    "taxon_id": 203153
  },
  "c1dcae59-c6c1-45ea-a87b-909735e4348d": {
    "created_at": "2025-09-17",
    "faves_count": 1,
    "taxon_id": 203153
  },
  "e7101d35-723a-40bb-a14c-e5061c9db1c5": {
    "created_at": "2025-09-17",
    "faves_count": 1,
    "taxon_id": 116804
  },
  "143b9d66-0546-4a2c-8a46-c0fb6b3d0339": {
    "created_at": "2025-09-14",
    "faves_count": 1,
    "taxon_id": 4788
  },
  "71ea87cc-7ddf-4fa4-ada6-369dfce733d8": {
    "created_at": "2025-09-12",
    "faves_count": 1,
    "taxon_id": 204552
  },
  "4dc26362-3a35-43cb-8960-273774f15501": {
    "created_at": "2025-09-09",
    "faves_count": 2,
    "taxon_id": 204552
  },
  "bd1d96f3-a785-4974-abb8-60d08417f35d": {
    "created_at": "2025-09-04",
    "faves_count": 1,
    "taxon_id": 7450
  },
  "02d0c0b9-959f-4468-9d87-6dcf3676a282": {
    "created_at": "2025-09-02",
    "faves_count": 1,
    "taxon_id": 12822
  },
  "6966e864-f23d-46b9-bdf8-9a24d002a05f": {
    "created_at": "2025-08-30",
    "faves_count": 1,
    "taxon_id": 3849
  },
  "c505cb9a-6ece-45a4-85d4-0eafb47aed6f": {
    "created_at": "2025-08-29",
    "faves_count": 1,
    "taxon_id": 3838
  },
  "a256ee78-fa44-4cd6-978e-3a18afaaa9c8": {
    "created_at": "2025-08-29",
    "faves_count": 1,
    "taxon_id": 19410
  },
  "3236c5f4-17d8-42cc-a6ce-93ec026d2826": {
    "created_at": "2025-08-29",
    "faves_count": 1,
    "taxon_id": 339593
  },
  "842d39c8-f3e6-4793-b7f3-2851c6f941d4": {
    "created_at": "2025-08-29",
    "faves_count": 1,
    "taxon_id": 5167
  },
  "cb65cd51-9b19-47f5-80dc-c5ec21f6303e": {
    "created_at": "2025-08-28",
    "faves_count": 1,
    "taxon_id": 19410
  },
  "86f29700-bc28-4938-9f52-33ae4e6f418e": {
    "created_at": "2025-08-25",
    "faves_count": 1,
    "taxon_id": 144757
  },
  "9bed64ac-75f7-4619-a84a-4c29fafd76f6": {
    "created_at": "2025-08-25",
    "faves_count": 1,
    "taxon_id": 629602
  },
  "4fc654f9-b9b9-495a-ac33-23f19259f07a": {
    "created_at": "2025-08-25",
    "faves_count": 1,
    "taxon_id": 13711
  },
  "8b14f303-b01d-4a3a-8d89-2525d211f884": {
    "created_at": "2025-08-24",
    "faves_count": 2,
    "taxon_id": 558443
  },
  "24e598b6-d183-4f00-aaed-eca31c9f6b1d": {
    "created_at": "2025-08-14",
    "faves_count": 1,
    "taxon_id": 12748
  },
  "93ee2191-a3f8-495d-a8a6-666170527211": {
    "created_at": "2025-08-12",
    "faves_count": 2,
    "taxon_id": 4647
  },
  "cbb3eda5-2419-4f8c-9efb-53c13abc1321": {
    "created_at": "2025-08-11",
    "faves_count": 1,
    "taxon_id": 482
  },
  "702920d1-f4ea-4da3-ad85-f90f7bb9ed8c": {
    "created_at": "2025-08-11",
    "faves_count": 1,
    "taxon_id": 558438
  },
  "04743ed0-0a45-49cb-93ac-c98a97c550b9": {
    "created_at": "2025-08-11",
    "faves_count": 1,
    "taxon_id": 6930
  },
  "38622d52-b1f6-4b6b-8fa8-6dba56112fca": {
    "created_at": "2025-08-11",
    "faves_count": 1,
    "taxon_id": 5325
  },
  "4202b7b2-cdb8-432e-a015-42e5784106d3": {
    "created_at": "2025-08-10",
    "faves_count": 2,
    "taxon_id": 15282
  },
  "e0b645b3-c819-4206-aeb3-019b8988bd0d": {
    "created_at": "2025-08-07",
    "faves_count": 1,
    "taxon_id": 201178
  },
  "d108f346-228b-4200-9fda-725f785b1677": {
    "created_at": "2025-08-06",
    "faves_count": 1,
    "taxon_id": 6638
  },
  "10921ddb-248e-44b6-a879-f285b47f5ced": {
    "created_at": "2025-12-11",
    "faves_count": 1,
    "taxon_id": 559070
  },
  "332d5b58-441e-4edb-8bc8-270ffe012af9": {
    "created_at": "2025-12-11",
    "faves_count": 2,
    "taxon_id": 7647
  },
  "2ec5d07c-462e-4270-addd-9450c7a1ef19": {
    "created_at": "2025-12-11",
    "faves_count": 1,
    "taxon_id": 558596
  },
  "6cd92426-befa-4926-8317-9fa63ab19cef": {
    "created_at": "2025-12-11",
    "faves_count": 1,
    "taxon_id": 558596
  },
  "b7161b55-0949-46ff-babe-5b2248500305": {
    "created_at": "2025-12-12",
    "faves_count": 1,
    "taxon_id": 558596
  },
  "f813de3c-d4ac-45e3-aa7c-c99565516f20": {
    "created_at": "2025-12-12",
    "faves_count": 1,
    "taxon_id": 145300
  },
  "dd38871b-bc96-494e-aace-9007a50a77ce": {
    "created_at": "2025-12-07",
    "faves_count": 1,
    "taxon_id": 4627
  },
  "cf365688-c7cc-4f4d-9894-2fa515df3bbc": {
    "created_at": "2025-12-14",
    "faves_count": 1,
    "taxon_id": 792977
  },
  "f2993c6c-ac24-4bdd-a507-763a83d27595": {
    "created_at": "2025-12-13",
    "faves_count": 1,
    "taxon_id": 558596
  },
  "dffb671b-d10d-4227-9dba-8a83dccbb7cb": {
    "created_at": "2025-12-13",
    "faves_count": 1,
    "taxon_id": 17943
  },
  "d60f1bd8-0587-4492-bd1a-456bd2dfbd7e": {
    "created_at": "2025-12-13",
    "faves_count": 3,
    "taxon_id": 1197386
  },
  "d11af24f-221d-49ae-9b55-b114e7259dce": {
    "created_at": "2025-12-13",
    "faves_count": 1,
    "taxon_id": 7429
  },
  "729f5faa-7218-477a-9d49-e42f1c31d800": {
    "created_at": "2025-12-13",
    "faves_count": 1,
    "taxon_id": 117016
  },
  "b6ea2bbb-0b49-4c22-b08c-22db05ff2272": {
    "created_at": "2025-12-14",
    "faves_count": 2,
    "taxon_id": 12707
  },
  "fea11951-b9d5-4e88-b4f1-6e7c754c4cc0": {
    "created_at": "2025-12-14",
    "faves_count": 1,
    "taxon_id": 7450
  },
  "f338cd88-dc55-45f7-b339-4e4a178e09b0": {
    "created_at": "2025-12-14",
    "faves_count": 1,
    "taxon_id": 7429
  },
  "c24abd1b-2cf9-40a9-b38b-472b6f336fa3": {
    "created_at": "2025-12-14",
    "faves_count": 2,
    "taxon_id": 145303
  },
  "a61181ff-0dda-4a26-b086-d4a4b2411d5f": {
    "created_at": "2025-12-14",
    "faves_count": 1,
    "taxon_id": 145300
  },
  "10fba5f3-3b85-4d9e-b28a-6c15c34277b1": {
    "created_at": "2025-12-14",
    "faves_count": 2,
    "taxon_id": 7009
  },
  "aa54d388-b451-4c5a-9f79-131dbcdea608": {
    "created_at": "2025-11-20",
    "faves_count": 1,
    "taxon_id": 145300
  },
  "1fd932c3-d749-44e2-b914-225dd2db96ac": {
    "created_at": "2025-12-15",
    "faves_count": 1,
    "taxon_id": 17943
  },
  "2bfd7e14-c1f8-4a68-9a75-7fe25bfb225d": {
    "created_at": "2025-12-15",
    "faves_count": 1,
    "taxon_id": 9201
  },
  "113d72d8-f4bf-4d2b-943c-471708c15230": {
    "created_at": "2025-12-17",
    "faves_count": 1,
    "taxon_id": 19890
  },
  "70f063c7-da4f-430d-b312-a41867f0ebab": {
    "created_at": "2025-12-16",
    "faves_count": 1,
    "taxon_id": 7429
  },
  "37233297-ebea-47df-bb2e-945d8078ce5e": {
    "created_at": "2025-12-14",
    "faves_count": 1,
    "taxon_id": 17943
  },
  "e7faf0c5-16d9-41de-b345-c26deef5faa9": {
    "created_at": "2025-12-17",
    "faves_count": 1,
    "taxon_id": 4627
  },
  "a170ed5c-a4a2-4081-a915-b4c18ea32550": {
    "created_at": "2025-12-17",
    "faves_count": 1,
    "taxon_id": 13075
  },
  "aa6c7f1e-53bf-4fe8-8e46-7a5af77748a9": {
    "created_at": "2025-12-17",
    "faves_count": 1,
    "taxon_id": 629602
  },
  "aa8e8806-d58f-4ce4-a484-1d7a1bf12046": {
    "created_at": "2025-12-17",
    "faves_count": 1,
    "taxon_id": 4643
  },
  "f1bb0acf-9a6e-4d02-abe4-63431cb864e6": {
    "created_at": "2025-12-19",
    "faves_count": 1,
    "taxon_id": 7429
  },
  "765d7751-c3b7-4fc4-9c6d-a08b8e0c6dd8": {
    "created_at": "2025-12-18",
    "faves_count": 1,
    "taxon_id": 558634
  },
  "2f22b6d3-921c-4dcb-a034-9791da250231": {
    "created_at": "2025-12-15",
    "faves_count": 1,
    "taxon_id": 7004
  },
  "f1e50182-d9e0-4eb3-9013-1e50a53c2367": {
    "created_at": "2025-12-20",
    "faves_count": 1,
    "taxon_id": 10069
  },
  "cf444aa1-4433-4f90-bf9c-9b3c27f2873d": {
    "created_at": "2025-12-20",
    "faves_count": 1,
    "taxon_id": 203153
  },
  "e69ba5f9-cae3-43a7-b274-654c25b47bb5": {
    "created_at": "2025-12-20",
    "faves_count": 2,
    "taxon_id": 792977
  },
  "481155a4-b784-4f9a-959a-dd73ae82a05b": {
    "created_at": "2025-12-20",
    "faves_count": 1,
    "taxon_id": 8010
  },
  "7712e47a-e2f9-466e-bda7-5f29c05255c0": {
    "created_at": "2025-12-20",
    "faves_count": 1,
    "taxon_id": 6930
  },
  "803d0ca5-5634-4504-826e-cd367906e65b": {
    "created_at": "2025-12-20",
    "faves_count": 1,
    "taxon_id": 7004
  },
  "8221b72d-5d6d-47d7-9716-a2d343c07284": {
    "created_at": "2025-12-21",
    "faves_count": 1,
    "taxon_id": 8010
  },
  "b2435923-ce83-44ea-9f21-c5187014ddc3": {
    "created_at": "2025-12-22",
    "faves_count": 1,
    "taxon_id": 7450
  },
  "8d67e42e-65cb-4b13-a1d4-d6d8598dd715": {
    "created_at": "2025-12-22",
    "faves_count": 1,
    "taxon_id": 3048
  },
  "e05f6fa1-d86a-429d-9547-666f0a210e05": {
    "created_at": "2025-12-21",
    "faves_count": 1,
    "taxon_id": 7004
  },
  "8efb283b-a489-4d82-81cf-d8c65aa4475b": {
    "created_at": "2025-12-13",
    "faves_count": 1,
    "taxon_id": 3048
  },
  "2a31d4c1-023b-449f-b20b-9f82a564d5f0": {
    "created_at": "2025-11-16",
    "faves_count": 1,
    "taxon_id": 3048
  },
  "1d3ba89e-a049-4334-bfee-5564ea2194f3": {
    "created_at": "2025-12-24",
    "faves_count": 1,
    "taxon_id": 7647
  },
  "412712e8-0360-4f4b-a0fb-b5e68600bf01": {
    "created_at": "2025-12-25",
    "faves_count": 1,
    "taxon_id": 19910
  },
  "347d82cc-b078-414c-a6bb-69f8d435032a": {
    "created_at": "2025-12-26",
    "faves_count": 1,
    "taxon_id": 558596
  },
  "ba00f63b-abd1-4092-bba9-52492b7ab55b": {
    "created_at": "2025-12-28",
    "faves_count": 2,
    "taxon_id": 203153
  },
  "e3aa9fb6-4226-454a-ab60-4e718996b3af": {
    "created_at": "2025-12-27",
    "faves_count": 2,
    "taxon_id": 629602
  },
  "c67ebbe9-f321-442d-9cda-3ae7c981a3b2": {
    "created_at": "2025-12-27",
    "faves_count": 1,
    "taxon_id": 6930
  },
  "3c55d467-7461-4e63-96cf-9f913f3830b6": {
    "created_at": "2025-12-29",
    "faves_count": 1,
    "taxon_id": 1289470
  },
  "574a4af9-7f3a-4a77-921a-2e9e9b5a6ae6": {
    "created_at": "2025-12-29",
    "faves_count": 1,
    "taxon_id": 11901
  },
  "d2137279-92be-43d2-9186-2f4af52df5aa": {
    "created_at": "2025-12-31",
    "faves_count": 1,
    "taxon_id": 4450
  },
  "df128d12-0383-4430-9867-433d2a389c95": {
    "created_at": "2025-12-31",
    "faves_count": 1,
    "taxon_id": 17943
  },
  "96ca64de-5754-40ed-865c-2a2652b20f42": {
    "created_at": "2026-01-03",
    "faves_count": 1,
    "taxon_id": 19910
  },
  "95fc6f20-458a-4249-92df-355ae5ef4a7e": {
    "created_at": "2026-01-02",
    "faves_count": 1,
    "taxon_id": 17943
  },
  "572d7ce0-8a92-4984-a09b-45bd8062218f": {
    "created_at": "2026-01-02",
    "faves_count": 1,
    "taxon_id": 6990
  },
  "6e30ec29-461b-4593-b485-bcb6a3e7e6db": {
    "created_at": "2026-01-01",
    "faves_count": 1,
    "taxon_id": 497049
  },
  "671ffb99-8406-4b6f-b8a2-4953aa161945": {
    "created_at": "2025-12-31",
    "faves_count": 1,
    "taxon_id": 4627
  },
  "f1c7a232-c182-4b05-8089-612691078e96": {
    "created_at": "2026-01-03",
    "faves_count": 1,
    "taxon_id": 144757
  },
  "a03dfbd8-2908-4656-a146-fa783959465d": {
    "created_at": "2026-01-04",
    "faves_count": 3,
    "taxon_id": 7450
  },
  "8138d210-f185-4653-8125-5921f8efb9d8": {
    "created_at": "2026-01-07",
    "faves_count": 1,
    "taxon_id": 7429
  },
  "0699a079-0667-4f72-89eb-1f320380571d": {
    "created_at": "2026-01-06",
    "faves_count": 1,
    "taxon_id": 203153
  },
  "c4d7d65b-91b0-4804-9639-f52891be8d89": {
    "created_at": "2026-01-06",
    "faves_count": 1,
    "taxon_id": 5200
  },
  "1b21e441-b695-4cce-8ce6-735183f8e81a": {
    "created_at": "2026-01-06",
    "faves_count": 1,
    "taxon_id": 1026
  },
  "802be3c9-54a3-44b8-afe8-bf7b2e309583": {
    "created_at": "2026-01-06",
    "faves_count": 1,
    "taxon_id": 558596
  },
  "628190dc-d2d8-4b1e-b813-6531ad501834": {
    "created_at": "2026-01-05",
    "faves_count": 1,
    "taxon_id": 8010
  },
  "d1ec7c74-691d-47f6-8269-6e14912fe556": {
    "created_at": "2026-01-07",
    "faves_count": 3,
    "taxon_id": 3048
  },
  "f6f16775-26a5-419a-ad6a-98a7cb46a51d": {
    "created_at": "2026-01-08",
    "faves_count": 1,
    "taxon_id": 7429
  },
  "59dc0496-f849-4573-9217-95e6345497d8": {
    "created_at": "2026-01-08",
    "faves_count": 1,
    "taxon_id": 19848
  },
  "14a556b3-0a4a-4882-a8f3-9780c1439b9f": {
    "created_at": "2026-01-08",
    "faves_count": 1,
    "taxon_id": 558596
  },
  "ea7ffd0d-0976-4da5-acc5-67d06780d931": {
    "created_at": "2025-12-31",
    "faves_count": 1,
    "taxon_id": 4672
  },
  "890f8de7-a471-457a-9530-1fde43c93cd2": {
    "created_at": "2025-12-24",
    "faves_count": 1,
    "taxon_id": 558438
  },
  "f82db334-5445-49b6-aafc-8e6abc621eac": {
    "created_at": "2025-12-20",
    "faves_count": 1,
    "taxon_id": 558438
  },
  "ba4165af-4125-4300-b0be-b3c65f0a4714": {
    "created_at": "2026-01-09",
    "faves_count": 1,
    "taxon_id": 6930
  },
  "aa13a7f1-3209-41fd-aeaa-566e070d9856": {
    "created_at": "2026-01-11",
    "faves_count": 1,
    "taxon_id": 19910
  },
  "bc61a6d0-d279-4a5b-b9f9-7de769e5ea00": {
    "created_at": "2026-01-10",
    "faves_count": 1,
    "taxon_id": 145300
  },
  "4f6c02fe-2626-436b-b1d4-465111c9d1d5": {
    "created_at": "2026-01-10",
    "faves_count": 1,
    "taxon_id": 19910
  },
  "c3fa2f88-3eb3-40e7-98a8-cf88c72ddff4": {
    "created_at": "2026-01-10",
    "faves_count": 1,
    "taxon_id": 12707
  },
  "a35a24b0-5d5f-44fc-bbbd-a6f09bc7312b": {
    "created_at": "2026-01-12",
    "faves_count": 1,
    "taxon_id": 144809
  },
  "5b308867-aec0-4c08-bf18-36ac2f9ad892": {
    "created_at": "2026-01-11",
    "faves_count": 1,
    "taxon_id": 629602
  },
  "a7d7d931-cf52-432c-8693-dec24b149ca8": {
    "created_at": "2026-01-11",
    "faves_count": 1,
    "taxon_id": 339593
  },
  "da7ee054-3874-43af-b921-565fb8da9d1d": {
    "created_at": "2026-01-11",
    "faves_count": 1,
    "taxon_id": 4892
  },
  "ee7c488f-f5c5-4cf4-859f-2c98162641da": {
    "created_at": "2026-01-09",
    "faves_count": 1,
    "taxon_id": 10411
  },
  "d5948d81-ca63-4b14-bf0d-f259bff801e3": {
    "created_at": "2025-12-29",
    "faves_count": 1,
    "taxon_id": 144455
  },
  "e86a8d7e-3d10-4972-94e6-a4f16a8fed71": {
    "created_at": "2025-11-06",
    "faves_count": 1,
    "taxon_id": 117008
  },
  "bf5c08b7-2790-4ec3-8b88-84222d5829d7": {
    "created_at": "2025-09-05",
    "faves_count": 1,
    "taxon_id": 5382
  },
  "bd4f5d48-3af1-4d5d-adcf-4035b9ab14aa": {
    "created_at": "2026-01-14",
    "faves_count": 1,
    "taxon_id": 7647
  },
  "2d113c81-5aae-47c7-8eca-bafb34ccfb2f": {
    "created_at": "2026-01-13",
    "faves_count": 1,
    "taxon_id": 204552
  },
  "55445149-7c09-462f-97da-9ca94eabbf79": {
    "created_at": "2026-01-13",
    "faves_count": 1,
    "taxon_id": 5200
  },
  "b8109ea6-e2eb-4ee0-aa83-e269842fc000": {
    "created_at": "2025-12-22",
    "faves_count": 1,
    "taxon_id": 13000
  },
  "0b790e4a-803d-49d2-9de9-f589b4a9cf7b": {
    "created_at": "2026-01-15",
    "faves_count": 1,
    "taxon_id": 792977
  },
  "56469aec-7df8-42da-9893-1b562a695698": {
    "created_at": "2026-01-17",
    "faves_count": 1,
    "taxon_id": 145360
  },
  "4f6e6342-5d04-4901-b03a-9c13359a9846": {
    "created_at": "2026-01-17",
    "faves_count": 1,
    "taxon_id": 558443
  },
  "c0c6f0b4-aa4c-4fc7-a63b-789bec43cd76": {
    "created_at": "2026-01-10",
    "faves_count": 1,
    "taxon_id": 4647
  },
  "6ba98208-06e4-4892-9bd0-e03e3e54ca38": {
    "created_at": "2026-01-19",
    "faves_count": 1,
    "taxon_id": 8010
  },
  "d5600a0e-ccea-4046-8385-ff08847297a7": {
    "created_at": "2026-01-18",
    "faves_count": 1,
    "taxon_id": 4208
  },
  "cc2be789-6fdc-4357-9fcd-b85b67e84313": {
    "created_at": "2026-01-18",
    "faves_count": 1,
    "taxon_id": 145300
  },
  "9c2bbed9-5a3b-46cc-a8cf-3cdd79bac359": {
    "created_at": "2026-01-18",
    "faves_count": 1,
    "taxon_id": 729687
  },
  "6fb6d101-f55f-4abd-9912-9fcb9bde9cc2": {
    "created_at": "2026-01-20",
    "faves_count": 1,
    "taxon_id": 144809
  },
  "fff6dc7a-64bc-4b98-a918-53360515f1f5": {
    "created_at": "2026-01-20",
    "faves_count": 1,
    "taxon_id": 363896
  },
  "8f234a0d-d4f8-4217-b55d-a4986610f121": {
    "created_at": "2026-01-20",
    "faves_count": 1,
    "taxon_id": 6638
  },
  "625347f5-3efb-406f-b5c2-f3a0190c7e48": {
    "created_at": "2026-01-20",
    "faves_count": 1,
    "taxon_id": 559070
  },
  "87b50c33-15e4-474f-b2c2-54d869d3e796": {
    "created_at": "2025-10-25",
    "faves_count": 1,
    "taxon_id": 19910
  },
  "ca322cf0-12e6-4798-ac53-6d62a64292ed": {
    "created_at": "2026-01-22",
    "faves_count": 1,
    "taxon_id": 7429
  },
  "6727c5a7-f381-4c23-bf95-c588aebd8a13": {
    "created_at": "2026-01-24",
    "faves_count": 1,
    "taxon_id": 4672
  },
  "e6e9514e-eddf-465a-a947-13c8513b484c": {
    "created_at": "2026-01-23",
    "faves_count": 1,
    "taxon_id": 13858
  },
  "0f131ec5-d478-4bcb-8f1e-22d9ecf66bf9": {
    "created_at": "2026-01-23",
    "faves_count": 1,
    "taxon_id": 6916
  },
  "9db2a149-12df-4f05-abac-27df2911b68c": {
    "created_at": "2026-01-23",
    "faves_count": 1,
    "taxon_id": 17669
  },
  "c95655dc-e6fd-4c3a-a453-0c21c5d3054e": {
    "created_at": "2026-01-24",
    "faves_count": 1,
    "taxon_id": 4389
  },
  "ab9194fb-5e4b-4869-ab93-b81002e4a54e": {
    "created_at": "2026-01-24",
    "faves_count": 1,
    "taxon_id": 7450
  },
  "10787ca6-6771-4458-a368-359e90324187": {
    "created_at": "2026-01-24",
    "faves_count": 1,
    "taxon_id": 7450
  },
  "036f1c37-0a53-470c-8a31-d0520f0dccd5": {
    "created_at": "2026-01-24",
    "faves_count": 1,
    "taxon_id": 558596
  },
  "daadd9f4-2a48-497c-8c15-95d3ccdc5dc2": {
    "created_at": "2026-01-25",
    "faves_count": 1,
    "taxon_id": 17943
  },
  "0ac1962a-2600-42e5-b090-9da5c547958b": {
    "created_at": "2026-01-27",
    "faves_count": 1,
    "taxon_id": 558439
  },
  "25dce866-0015-46ae-bce5-ced8b3f650ad": {
    "created_at": "2026-01-26",
    "faves_count": 1,
    "taxon_id": 7647
  },
  "22303a47-523a-438b-a154-71411603d2b7": {
    "created_at": "2026-01-29",
    "faves_count": 1,
    "taxon_id": 8010
  },
  "3ebeb8a6-e8a2-407a-aff5-e3b0bcea1cc5": {
    "created_at": "2026-01-28",
    "faves_count": 1,
    "taxon_id": 19910
  },
  "55f6ff87-d7e9-4650-be8d-d74b81233e94": {
    "created_at": "2026-01-28",
    "faves_count": 1,
    "taxon_id": 7450
  },
  "bc56af0e-f1b8-42e0-956b-e85ddea24329": {
    "created_at": "2026-01-30",
    "faves_count": 1,
    "taxon_id": 558596
  },
  "3a353501-a777-4680-a9a6-af2e3d2a12ab": {
    "created_at": "2026-01-29",
    "faves_count": 1,
    "taxon_id": 6990
  },
  "5bc64ba8-3098-4c63-853e-75c3df397bdd": {
    "created_at": "2026-01-29",
    "faves_count": 1,
    "taxon_id": 339593
  }
}